{
  "cate": "3",
  "date": "7æ13æ¥ 6æ01å",
  "datetime": "2018-07-13T06:01",
  "video": "/news/html/20180713/movie/k10011530961_201807130651_201807130651.html",
  "duration": 60,
  "img": "html/20180713/K10011530961_1807130651_1807130651_01_03.jpg",
  "title": "日本文化を紹介する行事「ジャポニスム2018」仏で開幕",
  "summary": "フランスで日本文化を紹介する行事、「ジャポニスム2018」が開幕し、開会式に出席した河野外務大臣は「１人でも多くの人に、日本文化の粋を堪能してもらいたい」と呼びかけました。",
  "more": "「ジャポニスム2018」は、日本とフランスが外交関係を樹立して160年になるのを記念して、今月から来年２月にかけて、フランス各地で日本の美術品の展示や伝統芸能の公演などを行うもので日本文化を発信する行事としては過去最大の規模となります。<br /><br />日本時間の13日未明、パリで行われた開会式には、豪雨による災害対応のため海外出張を取りやめた安倍総理大臣に代わって、河野外務大臣が出席しました。<br /><br />式典のあいさつで、河野大臣は「フランスと日本の間には、実に独特な、心と心で結ばれた文化の長い歴史があり、文化を通して互いに高めあい、価値観を共有した。１人でも多くの人に、日本文化の粋を堪能してもらいたい」と呼びかけました。<br /><br />また、フランスのニセン文化相は「今回のイベントは、日仏両国の歴史ある、たぐいまれな関係を具体化したもので、非常にうれしく思っている。マクロン大統領は、日本でもフランスの文化イベントを開催することを望んでいる」と述べました。",
  "body": [
    {
      "title": "",
      "img": "",
      "align": "",
      "text": "",
      "textPos": ""
    }
  ],
  "relationNews": [],
  "relationLink": [
    {
      "link": "https://www3.nhk.or.jp/news/special/international-news/breakfast/",
      "title": "朝食前のあなたに…ちょっと気になる国際ニュース",
      "time": "",
      "datetime": ""
    },
    {
      "link": "https://www3.nhk.or.jp/news/easy/k10011530961000/k10011530961000.html",
      "title": "フランスで日本文化を紹介するイベントが始まる",
      "time": "NEWSWEB EASY 7月17日",
      "datetime": "2018-07-17"
    }
  ],
  "word": [
    {
      "link": "word/0000564.html",
      "title": "国際５"
    }
  ],
  "news_id": "k10011530961000",
  "yyyy": "2018",
  "mm": "07",
  "dd": "13",
  "url": "https://www3.nhk.or.jp/news/html/20180713/k10011530961000.html"
}