{
  "news_id": "k10011535931000",
  "news_prearranged_time": "2018-07-18 11:30:00",
  "title": "日本のジェット機「ＭＲＪ」がイギリスのイベントで飛ぶ",
  "title_with_ruby": "<ruby>日本<rt>にっぽん</rt></ruby>のジェット<ruby>機<rt>き</rt></ruby>「ＭＲＪ」がイギリスのイベントで<ruby>飛<rt>と</rt></ruby>ぶ",
  "outline_with_ruby": "<p><ruby>三菱重工業<rt>みつびしじゅうこうぎょう</rt></ruby>の<a href='javascript:void(0)' class='dicWin' id='id-0002'>グループ</a>の<ruby>会社<rt>かいしゃ</rt></ruby>の<ruby>三菱航空機<rt>みつびしこうくうき</rt></ruby>は<ruby>日本<rt>にっぽん</rt></ruby>で<ruby>初<rt>はじ</rt></ruby>めて、<ruby>客<rt>きゃく</rt></ruby>を<a href='javascript:void(0)' class='dicWin' id='id-0003'><ruby>乗<rt>の</rt></ruby>せる</a>ための<a href='javascript:void(0)' class='dicWin' id='id-0000'>ジェット<ruby>機<rt>き</rt></ruby></a>をつくっています。",
  "has_news_web_image": true,
  "has_news_web_movie": true,
  "has_news_easy_image": false,
  "has_news_easy_movie": false,
  "has_news_easy_voice": true,
  "news_web_image_uri": "https://www3.nhk.or.jp/news/html/20180717/../20180717/K10011535931_1807170542_1807170543_01_03.jpg",
  "news_web_movie_uri": "k10011535931_201807170542_201807170543.mp4",
  "news_easy_image_uri": "''",
  "news_easy_movie_uri": "''",
  "news_easy_voice_uri": "k10011535931000.mp4",
  "url": "http://www3.nhk.or.jp/news/easy/k10011535931000/k10011535931000.html"
}