{
  "cate": "2",
  "date": "7æ19æ¥ 18æ40å",
  "datetime": "2018-07-19T18:40",
  "video": "/news/html/20180719/movie/k10011540111_201807191837_201807191839.html",
  "duration": 190,
  "img": "html/20180719/K10011540111_1807191837_1807191840_01_03.jpg",
  "title": "東京五輪で注目 “ダガヤサンドウ”って？",
  "summary": "今月24日で、東京オリンピックの開催まで２年となるのを前に、メインスタジアムの新国立競技場に近い東京 千駄ヶ谷の周辺は個性的な飲食店や専門店が次々と出店し、「ダガヤサンドウ」の愛称で注目を集めています。",
  "more": "「ダガヤサンドウ」は、東京オリンピック・パラリンピックのメインスタジアムでおよそ６万人が観戦できる新国立競技場に近い千駄ヶ谷と北参道の周辺をあわせたエリアで、日本将棋連盟や鳩森八幡神社のほか昔ながらの商店街や住宅街なども残る地域です。<br /><br />スタジアムの建設が進むなか、ここ数年、飲食店をはじめ、衣料品や雑貨、化粧品などを扱う個性的な専門店が次々と出店し、現在ではおよそ100軒の店が点在するまでになり、多くの若者が訪れています。<br /><br />このうち、スパイス料理の店「ＨＡＴＯＮＯＭＯＲＩ」は、カレーをはじめ、スパイスやハーブを使った世界各国の料理を提供していて、１つのプレートに数種類のカレーがのせられ、好みの味をいちどに楽しむことができます。<br /><br />また、ソフトクリームとカフェの店「レティエ」は、季節にあわせて商品にのせるフルーツやトッピングを変え見た目にも華やかなことからインスタ映えすると人気で、スマートフォンで撮影しようと多くの客が訪れています。<br /><br />ダガヤサンドウを訪れた23歳の女性は、「“ダガヤサンドウ”には初めて来ましたが、散歩しながらいろいろな店を楽しめました」と話していました。<br /><br />千駄ヶ谷大通り商店街振興組合の岡崎千治理事は、「新国立競技場を中心に、街が変わってきつつある。ぜひ多くの人にダガヤサンドウを訪れもらい、この地域がさらに活気づいてほしい」と話していました。",
  "body": [
    {
      "title": "",
      "img": "",
      "align": "",
      "text": "",
      "textPos": ""
    }
  ],
  "relationNews": [
    {
      "link": "html/20180718/k10011538141000.html",
      "title": "東京五輪まで２年 建設進む新国立競技場 公開",
      "date": "7月18日  16時10分",
      "datetime": "2018-07-18T16:10",
      "imgPath": "html/20180718/K10011538141_1807181603_1807181610_01_03.jpg",
      "iconPath": "html/20180718/K10011538141_1807181603_1807181610_02_01.jpg",
      "video": "https://www3.nhk.or.jp/news/html/20180718/movie/k10011538141_201807181603_201807181607.html",
      "duration": 44
    },
    {
      "link": "html/20180717/k10011536901000.html",
      "title": "東京五輪・パラまで２年 会場や選手村の工事現場公開",
      "date": "7月17日  17時31分",
      "datetime": "2018-07-17T17:31",
      "imgPath": "html/20180717/K10011536901_1807171858_1807171923_01_03.jpg",
      "iconPath": "html/20180717/K10011536901_1807171858_1807171923_02_01.jpg",
      "video": "https://www3.nhk.or.jp/news/html/20180717/movie/k10011536901_201807171858_201807171923.html",
      "duration": 146
    }
  ],
  "relationLink": [
    {
      "link": "https://www3.nhk.or.jp/news/special/mirai/",
      "title": "ぜんぶわかる 東京五輪・パラ",
      "time": "スペシャルコンテンツ",
      "datetime": ""
    }
  ],
  "word": [
    {
      "link": "word/0000271.html",
      "title": "東京五輪・パラ"
    }
  ],
  "news_id": "k10011540111000",
  "yyyy": "2018",
  "mm": "07",
  "dd": "19",
  "url": "https://www3.nhk.or.jp/news/html/20180719/k10011540111000.html"
}